csvmatch-2.1.0.dist-info/METADATA
csvmatch-2.1.0.dist-info/WHEEL
csvmatch-2.1.0.dist-info/entry_points.txt
csvmatch-2.1.0.dist-info/licenses/LICENCE
csvmatch/__init__.py
csvmatch/cli.py
csvmatch/cli_renderer.py
csvmatch/typings.py
csvmatch-2.1.0.dist-info/RECORD
