Metadata-Version: 2.4
Name: csvmatch
Version: 2.1.0
Summary: Find fuzzy matches between CSV files.
Author-Email: Max Harlow <contact@maxharlow.com>
License-Expression: Apache-2.0
Project-URL: source, https://github.com/maxharlow/csvmatch
Requires-Python: ==3.13.*
Requires-Dist: textmatch==1.1.*
Requires-Dist: polars[pandas,pyarrow]==1.21.*
Requires-Dist: chardet==5.2.*
Requires-Dist: colorama==0.4.*
Requires-Dist: tqdm==4.67.*
